argos_tracker/__init__.py
argos_tracker/fairness.py
argos_tracker/metrics.py
argos_tracker/reports.py
argos_tracker/store.py
argos_tracker/subcohort.py
argos_tracker/tracker.py
argos_tracker/utils.py
argos_tracker/jinja/__init__.py
argos_tracker/reports_dashboard/dist/spa/favicon.ico
argos_tracker/reports_dashboard/dist/spa/index.html
argos_tracker/reports_dashboard/dist/spa/assets/ErrorNotFound.74a937ee.js
argos_tracker/reports_dashboard/dist/spa/assets/IndexPage.b51839b5.js
argos_tracker/reports_dashboard/dist/spa/assets/IndexPage.f95c1f09.css
argos_tracker/reports_dashboard/dist/spa/assets/KFOkCnqEu92Fr1MmgVxIIzQ.34e9582c.woff
argos_tracker/reports_dashboard/dist/spa/assets/KFOlCnqEu92Fr1MmEU9fBBc-.9ce7f3ac.woff
argos_tracker/reports_dashboard/dist/spa/assets/KFOlCnqEu92Fr1MmSU5fBBc-.bf14c7d7.woff
argos_tracker/reports_dashboard/dist/spa/assets/KFOlCnqEu92Fr1MmWUlfBBc-.e0fd57c0.woff
argos_tracker/reports_dashboard/dist/spa/assets/KFOlCnqEu92Fr1MmYUtfBBc-.f6537e32.woff
argos_tracker/reports_dashboard/dist/spa/assets/KFOmCnqEu92Fr1Mu4mxM.f2abf7fb.woff
argos_tracker/reports_dashboard/dist/spa/assets/MainLayout.b9f67fc9.js
argos_tracker/reports_dashboard/dist/spa/assets/QBtn.dd872fc6.js
argos_tracker/reports_dashboard/dist/spa/assets/axios.d764c534.js
argos_tracker/reports_dashboard/dist/spa/assets/dom.44408ff4.js
argos_tracker/reports_dashboard/dist/spa/assets/example_data_drift_charts.65f1ad2d.png
argos_tracker/reports_dashboard/dist/spa/assets/fa-brands-400.232c6f6a.woff2
argos_tracker/reports_dashboard/dist/spa/assets/fa-brands-400.e28096fa.ttf
argos_tracker/reports_dashboard/dist/spa/assets/fa-regular-400.9174757e.ttf
argos_tracker/reports_dashboard/dist/spa/assets/fa-regular-400.c27da6f8.woff2
argos_tracker/reports_dashboard/dist/spa/assets/fa-solid-900.ae17c16a.woff2
argos_tracker/reports_dashboard/dist/spa/assets/fa-solid-900.b4990d0d.ttf
argos_tracker/reports_dashboard/dist/spa/assets/fa-v4compatibility.c7a869fa.woff2
bbj_argos-0.0.1.dist-info/licenses/LICENSE
bbj_argos-0.0.1.dist-info/METADATA
bbj_argos-0.0.1.dist-info/WHEEL
bbj_argos-0.0.1.dist-info/entry_points.txt
bbj_argos-0.0.1.dist-info/top_level.txt
bbj_argos-0.0.1.dist-info/RECORD
